{"Reviews": [{"Title": "A WORKHORSE - GOING ON 5 YEARS 50-80 HOURS A WEEK", "Author": "E. B. MULLIGAN \"Bronwyn\"", "ReviewID": "R7EXCZB39E0S7", "Overall": "5.0", "Content": "A WORKHORSE - GOING ON 5 YEARS 50-80 HOURS A WEEKI can't say enough good things. Dependable, sturdy, fine screen, good weight, decent speed, meets all my business needs, very low maintenance. Everything still in perfect working order 54 months later.* Wireless-N, based on 802.11n technology, with up to 5X the speed and 2X the range of traditional Wi-Fi\u00ae when used with a Wireless-N router3* Display WXGA+ (1440 x 900 resolution) WXGA (1280 x 800 resolution)* HyperBand Diversity Antenna delivers superior multi-band wireless performance for mobile broadband and Wi-Fi* Integrated Bluetooth 2.0 with Enhanced Data Rate makes it easy to connect personal devices* Built-in Dell WiFi Catcher(tm) Utility switch lets you quickly find a network, even when the laptop's closed* The latest Intel\u00ae Core(tm)2 Duo processors, with Intel integrated graphics for optimal battery life.* Genuine Windows Vista\u00ae Business or Genuine Windows\u00ae XP Professional* Performance hard-drive options including 7200 RPM, Hybrid hard drive* Power Supply: 65 Watt or 90 Watt AC adapter with cord wrappingBatteries featuring ExpressCharge(tm) : Primary 4-cell/32 WHr; Primary 6-cell/56 WHr; Primary 9-cell/85 WHr with 90 watt AC adapter; Secondary 6-cell/48 WHr \"Smart\" Li-Polymer batteryWEIGHT & DIMENSIONS: Starting at: 4.37lbs/1.98kg Width: 13.27\"/337.1mm Depth: 9.37\"/238mm Height: 1.26\"/32mm* PC Card: One Type I or Type II; Supports 34mm ExpressCard via USB interface through PCMCIA adapterPorts: Serial, docking connector, 4 USB, 1394, VGA, headphone/speaker out, RJ-11, RJ-45, AC power, integrated microphoneDocking: D/Port, D/Dock, D/View Laptop Stand, D/Monitor StandModular Options: DVDROM, 24X CD-ROM, 8X DVD +/-RW7, 24X CDRW/DVD, Floppy Disk Drive, Secondary 6-cell battery, 80GB8 Hard Drive or Travel Lite Module* Wired: Wired: 56K v924 Internal Modem 10/100/1000 Gigabit6 Ethernet network interface adaptorWireless: Dell Wireless 5520 Mobile Broadband (Tri-band HSDPA 3.6) Mini-Card with service from AT&T; (US) and Vodafone (select countries in Europe) Dell Wireless 5720 Mobile Broadband (EVDO Rev A) Mini-Card with service from Verizon Wireless (US), Sprint (US) and Telus (Canada)WLAN Dell Wireless 1390 (802.11g); Dell Wireless 1490 (802.11a/g); Dell Wireless 1505 (802.11a/g/Draft n); Intel PRO/Wireless 3945AG (802.11a/g); Intel PRO/Wireless 4965AGN (802.11a/g/ Draft n) Mini-Cards, Dell Wireless 360 Bluetooth 2.0 internal wireless card (upgradable to Bluetooth 2.1 EDR) (optional).TNVIDIA Quadro NVS 135M offers all the latest graphics technology to produce extraordinary visual effects, robust wide-aspect LCD support and compatibility with all major business applications.Intel\u00ae Graphics Media Accelerator X3100 (Up to 256MB shared5) is an intelligent and responsive graphics engine built into the chipset that is on the motherboard. This integration provides incredible visual quality, faster graphics performance and flexible display options", "Date": "June 2, 2012"}], "ProductInfo": {"Price": null, "Features": null, "Name": null, "ImgURL": null, "ProductID": "B0083M14ZW"}}