{"Reviews": [{"Title": "product delivered as advertised.", "Author": "Navissa Kaiser", "ReviewID": "R3V29IJW8WBL4T", "Overall": "5.0", "Content": "enjoying the long battery life and matt screen. great for writers. arrived packaged nicely and everything works so far. great product.", "Date": "July 20, 2013"}, {"Title": "Best Laptop on the market.", "Author": "G. Baim", "ReviewID": "R2G25DAXJ59G6Y", "Overall": "5.0", "Content": "Lenovo (IBM) Think Pads have always been the best made laptop. Innovations and reliability are first class. I would never consider any other laptop to purchase. The keyboard is excellent. This should be your \"only choice.\"", "Date": "February 17, 2013"}], "ProductInfo": {"Price": "$1,349.00", "Features": "Lenovo ThinkPad T430s Notebook PC", "Name": "ThinkPad T430s 23539MU 14\" LED Notebook - Intel - Core i5 i5-3320M 2.6GHz - Black", "ImgURL": "http://ecx.images-amazon.com/images/I/41ZwThpTAOL._SX300_.jpg", "ProductID": "B009UEU1YW"}}