{"Reviews": [], "ProductInfo": {"Price": "$1,425.00", "Features": "15.6\" FHD 16:9 LED Backlit Wide screen (1920x1080) Super Clear Glare Type Sager Screen\n4th Generation Intel\u00ae Haswell CoreTM i7-4910MQ (2.9GHz - 3.9GHz, 8MB Intel\u00ae Smart Cache)\nNVIDIA\u00ae GeForceTM GTX 850M (2.0GB) GDDR3 PCI-Express DX11 w/ OptimusTM Technology\n8GB DDR3 1600MHz [1x8GB] Dual Channel Memory / 750GB 7200RPM [SATA II - 16MB Cache] / 8X Super Multi DVDRW/CDRW Combo Drive (Sager) (Dual Layer w/ Software) / Built-in 802.11 Wireless B/G/N - Stock Wireless Card + BluetoothTM 4.0\nWindows 8.1 - 64-Bit (64-Bit CD Included) + MS Office 2013 Trial / 1 Year manufacturers warranty", "Name": "Sager NP6658 (Bulit off Clevo W650SS) 15.6\" Notebook computer / i7-4910MQ / Nvidia GT 850M", "ImgURL": "http://ecx.images-amazon.com/images/I/415E3YYJrrL._SX300_.jpg", "ProductID": "B00JJXY8MU"}}