{"Reviews": [{"Title": "LG Digital Zoom CCTV camera", "Author": "Jerry Jones", "ReviewID": "R2EI2849APB7QC", "Overall": "3.0", "Content": "Camera is OK, but not great.It is relatively easy to setup, but I washoping for a better picture at night.", "Date": "October 2, 2013"}], "ProductInfo": {"Price": "$179.99", "Features": "650TVL Color Exview HAD CCD II with LG XDI-V processor\nSuper low LUX: 0.000001Lux(B/W) @ Sens-up x512\nICR Day & Night with 2D+3D DNR\nC/CS Mount; Lens not included\nRS-485 and Coaxial Communication; DC12V/AC24V", "Name": "LG LCB5300 650TVL Color XDI-V Day/Night 16x Digital Zoom Dual Voltage Box Camera with ICR, Lens not included (Silver Gray)", "ImgURL": "http://ecx.images-amazon.com/images/I/41v2R2VSjZL._SX300_.jpg", "ProductID": "B009FCYQ22"}}