{"Reviews": [{"Title": "BEST BANG FOR THE BUCK", "Author": "Rosendo Dimas \"someone in texas\"", "ReviewID": "R3NX8UB9QE8YDH", "Overall": "5.0", "Content": "CANT BEAT THIS 8CH DVR FOR THE MONEY WITH A 500GB HD, WORKS PERFECT LOVE IT. SHOPED EVERY WHERE BUT AMAZON WAS THE BEST PRICE AND THEY SHIPPED SUPER FAST.", "Date": "January 23, 2013"}, {"Title": "It works awesome", "Author": "Dustin Byce", "ReviewID": "R1PYG8IWUTSBJU", "Overall": "4.0", "Content": "It's a great DVR the only problem i have it the mouse is just too sensitive but other than that it works great.", "Date": "August 27, 2013"}], "ProductInfo": {"Price": "$289.99", "Features": "View Video Online with No Service Fees - View your DVR's live or recorded video footage on any PC.\nLong time recording: - Base on the H.264 Compression, maximize the hard drive's recording time, as well as transfer video for viewing over the internet.\nNetwork Remote Access - Access live video footage directly from your mobile phone or PC anytime anywhere\nAdvanced Motion Detection Recording - This allows you record only when motion is detected.\nInstant Email Alerts if Activity Detected - This system is designed to send an email alert, complete with photo of the activity, if any motion is detected, or if any camera experiences video loss.", "Name": "Zmodo 8 CH CCTV Security Surveillance DVR Record System 500GB Hard Drive", "ImgURL": "http://ecx.images-amazon.com/images/I/31FsE8RZOvL._SY300_.jpg", "ProductID": "B0095PCGW6"}}