{"Reviews": [], "ProductInfo": {"Price": "$55.39", "Features": "1. Wi-Fi compliant with wireless standards IEEE802.11b/g. Free DDNS bounded.\n2. Support M-JPEGCompression format Video. 1,4,9,16,25,36 multiple video display optional in one screen, support record, alarm, remote playback on records and other management functions.\n3. \u00a6\u00b55x10 IR-LED, automatic operate for night vision. (Up to 10 meters)Motion detection alert via email or upload image to FTP.\n4. Support multi kinds of network connection methods: fixed IP, DHCP, PPPOE.Supports two-level password: administrator authority, user authority.\n5. All our items are 100% tested and in Good working condition, so the quality is guaranteed. Please purchase with confidence.", "Name": "DBPOWER IP CAMERA WIRELESS MOTION SECURITY WIFI REMOTE CONTROL", "ImgURL": "http://ecx.images-amazon.com/images/I/31oy00e20gL._SY300_.jpg", "ProductID": "B00ATVYHS6"}}