{"Reviews": [{"Title": "affordable and dependable", "Author": "dale dickerson", "ReviewID": "R1QZ0FGVZJH2PP", "Overall": "5.0", "Content": "my second system.. if you are looking for an affordable, dependable, and upgradable system this would be the way to go... between a friend and myself we have four we use regularly", "Date": "November 27, 2013"}], "ProductInfo": {"Price": "$328.50", "Features": "Zmodo Surveillance KDA4-BARQZ4ZN-5G CCTV\n4Channel DVR\nH.264\n500GB HD and 4x 480TVL\nDay/Night CMOS Camera", "Name": "Zmodo 4CH D1 Security DVR Surveillance Camera System With 4 Outdoor Night Vision IR Security Cameras With 500GB HD", "ImgURL": "http://ecx.images-amazon.com/images/I/51R10G9ebFL._SY300_.jpg", "ProductID": "B00AYSI53C"}}