{"Reviews": [{"Title": "Nice DVR and easy to use", "Author": "Brian Lynch", "ReviewID": "R1QB9KIQP65U2N", "Overall": "5.0", "Content": "I bought 3 of these for a job we are doing at a Housing Development. Wow is all I can say. Lots of features and the layout is very simple to use. Now, we are not using the port forwarding feature for remote view but as a stand alone DVR, It is very nice.", "Date": "October 16, 2013"}], "ProductInfo": {"Price": "$199.99", "Features": "Compression algorithm upgraded to H.264 High Profile, more  advanced video compression technique makes the code stream lowered at least  30%.\nCompletely new graphics operating interface design, to  let you experience easily and conveniently.\nSuper strong processing capacity: can realize 8CH D1 recording .\nPowerful net service(support DHCP, PPPOE, FTP, DNS, DDNS, ARSP, NTP, UPNP, EMAIL, IP  authority, IP search, alarm center, etc), complete enclosure(WEB, CMS, SDK) to  easily achieve interconnection.\n1 Year Warranty only if you purchase from Evertech USA Corp.", "Name": "Evertech 8 Channel Real-time Hdmi DVR H.264 Full D1 High-definition Recording 1tb HDD Installed", "ImgURL": "http://ecx.images-amazon.com/images/I/41wPv1vF1vL._SY300_.jpg", "ProductID": "B00CHPVSC0"}}