{"Reviews": [], "ProductInfo": {"Price": "$409.99", "Features": "Use the standard H.264 video compression format stream lower,high quality,longer recording time, taking up less bandwidth resources\nSupport 4ch Full D1 realtime recording resolution,ahead to D1 High-Definition period.\nSony Super HAD Color CCD 700 TVL Bullet Cameras\nDual-stream design,network remote view effects and local recording effects parameters can be set separately,independently of each other.\nSystem auto recovery to power after power reconnected,and return to the pre-power-down state", "Name": "Evertech 4CH H.264 Video Compression format CCTV Surveillance Security DVR Camera System with 4 Sony Super HAD White Color 700TVL CCD Bullet Cameras-1TB HDD", "ImgURL": "http://ecx.images-amazon.com/images/I/51ZuWxoh-rL._SY300_.jpg", "ProductID": "B00DGZ3DFK"}}