{"Reviews": [{"Title": "excellent sign, even better customer service...", "Author": "Justin R.", "ReviewID": "R2NZ7HJJ0YW0YB", "Overall": "5.0", "Content": null, "Date": "January 3, 2014"}], "ProductInfo": {"Price": "Unavailable", "Features": "21st Century Digital Recording, Video over the Net Advisal\nREFLECTIVE COMMERCIAL GRADE UV FADE RESISTANT PLASTIC\nIncrease & Enhance your Security Deterrence\nSign Measures app 11\"x14\", Comes with 2 Mounting Holes, made in the USA\nMatching Deca;s, Signs on Stakes and Sign/Decal Kits Available", "Name": "1 VAS #140 Security Sign 21st Century  Warning Sign for Video Alarm Security Surveillance", "ImgURL": "http://ecx.images-amazon.com/images/I/51EwFXRrDQL._SX300_.jpg", "ProductID": "B00E1HH10U"}}