{"Reviews": [], "ProductInfo": {"Price": "$799.00", "Features": "iSmart 24CH CCTV H.264 Security DVR System 1TB HDD\nPlug & Play feature requires only ID and Password to set up.\nLive view or Playback recorded video via Smartphones, Tablets, PC and Mac.\nMotion detected, time shcheduled & continuous recording mode.\nHard disk hibernation technology, HDD faulty alarm & Raid (Redundancy)\n24CH D1 Standalone DVR\nDual-core CPU presents the powerful preview, recording, playback and network performance\nH.264 dual-stream video compression\nHDMI / VGA / CVBS/(BNC) synchronous video output\nAll channel simultaneous realtime playback, smart search\nSmart video detection: MD, camera blank, video loss\nAlarm triggering screen tips, buzzer, PTZ, e-mail & FTP upload\nSupport 2 SATA HDDs , 2 USB2.0\nBuilt-in web server, CMS(DSS/PSS) & DMSS", "Name": "iSmart 24CH CCTV H.264 Security DVR HDMI Video Out 1TB HDD", "ImgURL": "http://ecx.images-amazon.com/images/I/316vNm2ayIL._SY300_.jpg", "ProductID": "B00GS63J7G"}}