{"Reviews": [], "ProductInfo": {"Price": "Unavailable", "Features": "SUNLUXY 8 channel, fully integrated, real time, hardware-based digital video recorder.\nSupport Pan/Tilt/Zoom (PTZ) camera control, network access and USB2.0 backup.\nH.264 compression technology, record amazing quality video without using up a large amount of storage space.\nA variety of recording modes are supported: scheduled recording, motion detected recording, continuous recording, or a combination of any modes.\nSupport Remote View via smartphone & 3G Mobile with each of those systems a)Android ; b)iPhone & iPad IOS; c)Symbian ; d)Windows Mobile.", "Name": "SUNLUXY\u00ae 8 Channel H.264 Real Time DVR Recorder with 500GB Hard Drive for CCTV Security System", "ImgURL": "http://ecx.images-amazon.com/images/I/41zM7zP57oL._SY300_.jpg", "ProductID": "B00GRKIV5S"}}