{"Reviews": [], "ProductInfo": {"Price": "Unavailable", "Features": "1/4\" OV7930 CMOS\u00a0Wireless Security Camera; Weatherproof (Indoor/Outdoor)\nNight Vision up to\u00a026\u00a0feet\u00a0(with 11PCS Infrared LEDs); Clear Color Image (380 TV Line Resolution)\nWireless Receiver Supports up to\u00a04\u00a0Cameras; Built-in Microphone. (One Way Audio)\nCameras have Switchable Channels; Easy Installation:\u00a0Just Connect to Your TV or DVR\nWireless 2.4GHz Transmission\u00a0between Camera & Receiver up to\u00a0100m\u00a0(326ft)\u00a0in Open Space", "Name": "Brand New Kare L0108W4 Infrared Leds 2 Weatherproof Indoor/ Outdoor Wireless CCTV Security Camera System 4CH Receiver 8M Ir 100m Transmission", "ImgURL": "http://ecx.images-amazon.com/images/I/51hxG6XBctL._SY300_.jpg", "ProductID": "B00HJLSTUQ"}}