{"Reviews": [], "ProductInfo": {"Price": "$999.99", "Features": "Mobile phone / web ready  allows consumer to view video from remote locations\n8 channel system allows consumer to add up to 8 cameras and view simultaneously\n60-Feet of cable expands range for consumer use in the home or small business\nH.264 DVR provides advanced  video compression\nMaximum storage capacity  allows consumer to store 320 GB of media\nFirst Alert 4800 4 Wired Security Camera Recording System\n8-Channel System Allows Users To Add Up To 8 Cameras & View Simultaneously\nH.264 DVR Provides Advanced Video Compression\n320GB Maximum Storage Capacity\n40 Viewing Angle", "Name": "First Alert 4800 Four Wired Security Camera Recording System", "ImgURL": "http://ecx.images-amazon.com/images/I/41sZ6YitgIL._SY300_.jpg", "ProductID": "B003NCWPQO"}}