{"Reviews": [], "ProductInfo": {"Price": "$339.99", "Features": "This bundle includes 2 SVAT VIS300-7M2 hands free 2-wire color video intercom surveillance systems with 7\" LCD monitors and outdoor night vision security cameras\nWorks with your existing doorbell wiring so setup is fast and hassle-free\nSafely identify visitors with video and audio before deciding to answer the door\nEnjoy the convenience of hands free operation; Night vision camera gives you around the clock protection\nDoor strike compatibility allows you to remotely unlock your door; Wiring distance of 164'; 7\" LCD screen", "Name": "SVAT VIS300-7M2 Hands Free 2-Wire Color Video Intercom Surveillance System with 7\" LCD Monitor and Outdoor Night Vision Security Camera - Bonus Pack of 2", "ImgURL": "http://ecx.images-amazon.com/images/I/51qu7YA-VVL._SY300_.jpg", "ProductID": "B003C1FDG0"}}