{"Reviews": [{"Title": "Great little cameras", "Author": "Installer", "ReviewID": "R32E1N8H8U2HNR", "Overall": "4.0", "Content": "They work great! Good picture, good night vision. All plastic construction, but it seems like it will be durable. Remember these are indoor only cameras.", "Date": "January 31, 2013"}], "ProductInfo": {"Price": "$119.00", "Features": "Four Sharp 1/3 CCD 420TVL Color Indoor Dome Camera Infrared Day / Night Vision\nManual Pan / Tilt for with Wall mount and Celling mount\n24 infra-red LEDs see in the dark up to 50-65ft.\nOperates in freezing temperatures down to 4\u00b0F(-20\u00b0C)\nOne Year Warranty Guaranteed", "Name": "CIB CUC8401-4 420TVL indoor CCD Dome IR Day Night Security Camera Sharp Sensor.", "ImgURL": "http://ecx.images-amazon.com/images/I/51bsERKX3oL._SY300_.jpg", "ProductID": "B0036L5HAS"}}