{"Reviews": [{"Title": "This camera is great!", "Author": "JustSteve", "ReviewID": "RRLHS0BE4U4YC", "Overall": "5.0", "Content": "I use this camera all the time for my car hobby, my radio control helicopter events, and everything else I do. It's great, takes great photos, and it's easy to use. I have had mine for over two years with no problems at all. I like it so much I just bought one for my Mom's birthday a few weeks ago. Steve", "Date": "September 19, 2011"}], "ProductInfo": {"Price": "Unavailable", "Features": "Advanced Face Detection of up to 16 persons for perfectly focused and exposed faces plus correct exposure of other image areas\nDimensions (W x H x D): 92.7 x 55.8 x 24.7 mm\nWeight: 107 g (without battery and card)", "Name": "Olympus FE-5020 12MP Digital Camera with 5x Wide Angle Optical Zoom and 2.7 inch LCD (white)", "ImgURL": "http://ecx.images-amazon.com/images/I/41wMcGBSQzL._SX300_.jpg", "ProductID": "B004FGL46Y"}}