{"Reviews": [], "ProductInfo": {"Price": "$795.00", "Features": "Up to one year of operation in standby mode on a battery charge\nWireless operation\nMotion Activated\nWater resistant\nTruly the only product on the market for outside long term use\nProduct Specifications:\nVideo Input: NTSC/PAL Auto Detection\nStandby-time: Up to 365 days (1 Year)\nContinuous Usage: 20 hours\nRecord Mode: Standard, Motion, Overwrite\nMax DVR resolution is 720 x 480\nMin Illumination: 0.2LUX\nResolution Mode: 320x240 / 640x480 / 720x480\nFrame Rate: 1,5,15,20,25,30fps\nVideo Format: MPEG-4 ASF file format\nPicture Format: JPG\nStorage: SD Card (up to 16GB SDHC)\nFrame Counter Stamp: Yes\nBattery Type: 3.7V 15000mA Lithium Battery\nWeight: 1.2lbs\nSize: 4.75\"Lx3\"W x 1\" H\nCamera Specs:\nImage Sensor: 1/4\" CMOS\nResolution: 480 TV lines\nAngle of View: 78 degrees\nCamera: Color", "Name": "Xtremelife DVR/Battery with Camera", "ImgURL": "http://ecx.images-amazon.com/images/I/41bCI5taTTL._SY300_.jpg", "ProductID": "B004044756"}}