{"Reviews": [{"Title": "Good deal and average picture quality!!!", "Author": "Kevin Schutter", "ReviewID": "R2SFFKO0A9OUU6", "Overall": "4.0", "Content": "Worked just as stated.  Give decent video picture and are easy to use. Good deal and average picture quality thanks!!!", "Date": "October 16, 2013"}, {"Title": "Gret product for the price", "Author": "C. Cadeau \"Rainy lake\"", "ReviewID": "R1M8GDSKLL3AG1", "Overall": "4.0", "Content": "works great, no video issues for over a 60'+ cat5e run, a year plus and picture looks great! Good quality for the price, seems well made and fast ship as a Prime memeber.", "Date": "May 30, 2013"}, {"Title": "Excellent product!", "Author": "Philip Carlin", "ReviewID": "R25LL4JSTEUH6R", "Overall": "5.0", "Content": "Excellent product! Wire connection makes a very quick and clean installation! Vendor needs to have more product stocked by Amazon, lead time long when not stocked!", "Date": "October 12, 2011"}], "ProductInfo": {"Price": null, "Features": null, "Name": null, "ImgURL": null, "ProductID": "B004TLH22A"}}