{"Reviews": [], "ProductInfo": {"Price": "$602.45", "Features": "Built-in 1/3\" Sony Effio CCD security camera, high resolution of 700 TVL, enabling to obtain more natural high-definition video\nBuild-in 6-15mm Zoom Focus lens and 30 large infrared LEDs. NTSC system\nHeavy duty bracket, pan 360 degree, tilt 90 degrees\nWeatherproof aluminum outdoor housing, stand for use in all weather conditions. Real weatherproof housing resistant to heavy rain and snow\nPackage included: 1 x Sony CCD camera , 1 x security camera bracket , 1 x 12V DC power supply, 1 x video power extension camera cable and bonus security warning decal", "Name": "VideoSecu 700TVL CCTV Surveillance Security Camera Outdoor Built-in 1/3\" Sony Effio CCD DSP Day Night Zoom WDR Infrared 6-15mm Varifocal Lens for DVR Home Surveillance System, Including Power Supply, Security Camera Bracket, Extension Camera Cable and bonus Warning Sticker C88", "ImgURL": "http://ecx.images-amazon.com/images/I/41dhtkQH0kL.jpg", "ProductID": "B005Q59JD8"}}