{"Reviews": [], "ProductInfo": {"Price": "$499.99", "Features": "H.264 compression; Audio I/O; USB2.0 for back-up; remote view - IE based network monitoring\n4 cameras simultaneously digitally display and record at realtime; iPhone/mobile phone live view\nBuilt-in 10-Inch swivel LCD for easy viewing or connects to external TV (via BNC)\n500GB Surveillance Optimized Green Power hard drive installed and tested in USA for added reliability\nCapable of unattended operation over long period of time; remote control and mouse included\n10-inch LCD display\nH.264 compression; Audio I/O; USB2.0 for back-up; remote view - IE based network monitoring; 4 cameras simultaneously digitally display and record at realtime; iPhone/mobile phone live view\nBuilt-in swivel LCD for easy viewing or connects to external TV (via BNC)", "Name": "LTS LTD6104CDK 4-Camera H.264 Built-in 10-Inch Swivel LCD Realtime DVR Security System with 500GB/iPhone/Mobile Phone Live View", "ImgURL": "http://ecx.images-amazon.com/images/I/516gyZiJb6L._SY300_.jpg", "ProductID": "B005O7JZUA"}}