{"Reviews": [], "ProductInfo": {"Price": "$369.00", "Features": "100% IP67-rated (water and dust proof) Weatherproof IP Camera With Dedicated Free iPhone/iPad and Android Apps\nInfrared Night Vision to 15 metres\nBuilt-in SD card DVR expandable to 64Gb & Multi-zone Motion Sensor\nMotion Triggered Recordings and Alerts by email and FTP\nThe bullet range is equipped with Power over Ethernet support and can receive both power and data over a single Ethernet network cable. This allows the camera to be placed in areas that aren't close to a power outlet, optimising installation possibilities and making it perfect for installers and end users looking for a convertible and flexible solution. Please note: Using the POE capability of the camera requires the use of either a POE enabled switch/router/hub, or a separate POE injector to supply power to an Ethernet cable.", "Name": "TriVision NC-316P Weaterproof Outdoor IP Camera POE, Install in 3 steps with our iPhone, iPad and Android apps. 15m Night Vision, Motion Sensor, SD card DVR, and more", "ImgURL": "http://ecx.images-amazon.com/images/I/31OIUv1nXpL._SX300_.jpg", "ProductID": "B0068G01EU"}}