{"Reviews": [{"Title": "Awesome camera", "Author": "CHRISTINA JETER", "ReviewID": "RUDPOQ9J732HY", "Overall": "5.0", "Content": "Came in on time works great second one I bought as family loved it.  Accessories were great to come with it the bottle broke open but because of the well handled packaging it did not bother the rest of the items", "Date": "January 4, 2014"}], "ProductInfo": {"Price": "$234.99", "Features": "20.1MP 1/2.3\" Super HAD CCD Sensor\nSony 26x Optical Zoom Lens\n35mm Equivalent Focal Length: 22.3-580mm\n3.0\" 460k-Dot Clear Photo LCD Monitor\nHD 720p Video at 30fps\nOptical SteadyShot Image Stabilization\nPicture and Beauty Effect\n360\u00b0 Sweep Panorama\nFace Detection and Smile Shutter\nUses AA Batteries", "Name": "Sony Cyber-shot DSC-H200 Digital Camera 8GB Package 1", "ImgURL": "http://ecx.images-amazon.com/images/I/51XJTmo20qL._SY300_.jpg", "ProductID": "B00GT0QZ18"}}