{"Reviews": [{"Title": "Samsung Galaxy Note Sgh-i717", "Author": "Shelly N Martin", "ReviewID": "R6N4PW3T1I0Q3", "Overall": "2.0", "Content": "The phone looked great, however the phone has been slow and freezing a lot. I wish I could get another one.", "Date": "January 8, 2014"}, {"Title": "I simply LOVE my Note!", "Author": "Henry R.", "ReviewID": "RS3I2UEAAD97F", "Overall": "5.0", "Content": "I simply love my note! I love to draw and this is perfect for it! the S Pen is what makes buy it. sorry for my English", "Date": "October 5, 2013"}], "ProductInfo": {"Price": "Unavailable", "Features": "Android OS, v2.3 (Gingerbread), upgradable to v4.0 (Ice Cream Sandwich)", "Name": "Samsung Galaxy Note Sgh-i717 Black At&t 4g LTE Unlocked Cell Phone No Warranty - At&t Logos [At&t Retail Packaging]", "ImgURL": "http://ecx.images-amazon.com/images/I/51zWrAofaEL._SY300_.jpg", "ProductID": "B00BCR0I66"}}