{"Reviews": [{"Title": "the best looking windows phone and awesome speed and camera", "Author": "K. Kanaujia", "ReviewID": "R215ZRKPDC7A1X", "Overall": "5.0", "Content": "this is by far the best looking windows phone, even better then lumia 1020..if you compare with iPhone 5s, the lumia 925 standsout and has sharper and richer looks\u2026just my honest view\u2026i like iPhones but for the price there is no other phone that can come close to 925\u2026the live tiles make the look so much more fun on windows phone\u2026trust me, this phone in my view should be among the top 3 best smartphones in the world\u2026.its a shame that crowd mentality and less marketing does not let this device to be a top seller as yet..but we can see more and more people with windows phone and lumias\u2026", "Date": "December 20, 2013"}, {"Title": "This is an awesome phone!", "Author": "John", "ReviewID": "R3QPXTEBDK4THI", "Overall": "5.0", "Content": "Awesome phone!  Finally windows is coming through with useful, read to use products!  Solid, great feel in the hand, battery is longer than my Galaxy 3 \"with a few tweaks\".", "Date": "December 2, 2013"}], "ProductInfo": {"Price": null, "Features": null, "Name": null, "ImgURL": null, "ProductID": "B00F3JPKCG"}}