{"Reviews": [{"Title": "nice picture nice price", "Author": "Jameel Hackett \"neversurpassed\"", "ReviewID": "R7DGZGI8770MC", "Overall": "5.0", "Content": "Seller got it to me in two weeks across the country love the picture. Sound is ok but only has an optical output to go to a receiver. Changes inputs fast and has a fast warm up. It also needs good ventilation gets warm.", "Date": "January 5, 2011"}, {"Title": "Obviously pleased", "Author": "Huck", "ReviewID": "R3O0GZSRSZTQIY", "Overall": "5.0", "Content": "Largely pleased with this unit.  GREAT picture and super for the price.  Only drawback for me is that there is no closed caption function, which I do often need and there is only an optical output for sound which makes older sound enhancement devices unusable without some sort of optical to anologue converter.", "Date": "December 25, 2010"}], "ProductInfo": {"Price": "Unavailable", "Features": "Full HD 1080p\nNever miss a piece of the action.", "Name": "LG 60\" Plasma 180p 600Hz 2 HDMI Inputs", "ImgURL": "http://ecx.images-amazon.com/images/I/417T8aYx%2BzL._SY300_.jpg", "ProductID": "B0042FS12I"}}