{"Reviews": [{"Title": "You know how they say you get what you pay for?  This TV proves that", "Author": "Keith  Watson", "ReviewID": "RS06U78733TA2", "Overall": "5.0", "Content": "This is a great little 12vDC television.  Great picture and acceptable sound quality.  Hooked it up to the external antenna on my boat and got more than 35 channels--all crystal clear.The vendor--TreatYourBoatRight--was very responsive and shipped the same day I placed the order.Thanks Amazon!", "Date": "August 16, 2013"}], "ProductInfo": {"Price": "$285.00", "Features": "HD Ready Yes\nVoltage - Input Range (Volts) 12\nVoltage - Input Range (Volts) 12 VDC Power\nResolution (VxH) 1366 x 768 WXGA\nWaterproof Rating NONE", "Name": "Jensen Je1512Led 15\" Led Hdtv", "ImgURL": "http://ecx.images-amazon.com/images/I/51YY9GiXlcL._SY300_.jpg", "ProductID": "B004VCT770"}}