{"Reviews": [], "ProductInfo": {"Price": "$3,024.00", "Features": "Panel Technology SPVA (P-DID) Viewable Image Size 55\" Native Resolution 1920 x 1080 Pixel Pitch 0.63mm Backlight Type CCFL\nPixels Per Inch 40@ native resolution Brightness (typical) 500cd/m2 Brightness (maximum) 700cd/m2 Contrast Ratio (typical) 4000:1\nViewing Angle 178\u00b0 Vert., 178\u00b0 Hor. (89U/89D/89L/89R) @ CR>10 Response Time(Gray to Gray) 8ms Refresh Rate 60Hz Aspect Ratio 16:9\nActive Screen Area 47.6 x 26.8 in. / 1209.6 x 680.4mm Orientation Landscape/Portrait Displayable Colors More than 16.7 million\nPC Signal Compatibility Yes Macintosh Compatibility Yes\nBuilt-in expansion slot allows for seamless integration of NEC/third-party components, as well as future OPS-based products.\nExpanded connectivity with digital loop-through.\nFull 1080p high-definition resolution provides stunning detail.\nIndustrial-strength, premium-grade panel with additional thermal protection, internal temperature sensors with self-diagnostics and fan-based technology, allows for 24/7 operation.\nOpen Pluggable Specification is the industry's first standardized option slot that simplifies digital signage installations", "Name": "NEC P552 55-Inch 1080p 60Hz 3D LCD TV", "ImgURL": "http://ecx.images-amazon.com/images/I/41InBb05fCL._SX300_.jpg", "ProductID": "B0074FLTKY"}}